{
    "name": "badBoy.ent",
    "type": "enemy",
    "energy": 10,
    "strength": 5,
    "description": "this is another entity dummy",
    "x": 181,
    "y": 229,
    "dx": 2,
    "dy": 0,
    "path": -1,
    "pathEnd": "reverse loop",
    "pathStep": 1,
    "pathIdx": 0,
    "UP": "boyWalkUp",
    "LEFT": "boyWalkLeft",
    "DEFAULT": "boyWalkDown",
    "RIGHT": "boyWalkRight",
    "DOWN": "boyWalkDown",
    "APPEAR": "",
    "DISAPPEAR": "",
    "bounceHorizontally": true,
    "bounceVertically": true,
    "outOfHorizontalBoundaryRemove": false,
    "outOfVerticalBoundaryRemove": false,
    "collideWithPaddleRemove": false,
    "collideWithPaddleBounce": true,
    "BounceBallVertically": true,
    "BounceBallHorizontally": true,
    "collideBallRemoveBall": false,
    "collideBallAttacksBall": true,
    "collideBallLoseEnergy": true,
    "collidePaddleLoseEnergy": false
}