{
    "name": "forest1.ent",
    "type": "graphic",
    "energy": "",
    "strength": "",
    "description": "",
    "firstStateAt": 0,
    "states": [],
    "drawOnCanvas": "ground",
    "x": 0,
    "y": 0,
    "dx": 0,
    "dy": 0,
    "path": -1,
    "pathEnd": "loop",
    "pathStep": 0,
    "pathIdx": 0,
    "UP": "",
    "LEFT": "",
    "DEFAULT": "forest1.sprt",
    "RIGHT": "",
    "DOWN": "",
    "APPEAR": "",
    "DISAPPEAR": "",
    "bounceHorizontally": false,
    "bounceVertically": false,
    "outOfHorizontalBoundaryRemove": false,
    "outOfVerticalBoundaryRemove": false,
    "collideWithPaddleRemove": false,
    "collideWithPaddleBounce": false,
    "BounceBallVertically": false,
    "BounceBallHorizontally": false,
    "collideBallRemoveBall": false,
    "collideBallAttacksBall": false,
    "collideBallLoseEnergy": false,
    "collidePaddleLoseEnergy": false,
    "collideWithBWRemove": false,
    "collideWithBWBounce": false
}